eris/__init__.py
eris/base32.py
eris/coap.py
eris/crypto.py
eris/decoder.py
eris/encoder.py
eris/read_capability.py
eris/store.py
eris-1.0.0.dist-info/COPYING
eris-1.0.0.dist-info/METADATA
eris-1.0.0.dist-info/WHEEL
eris-1.0.0.dist-info/top_level.txt
eris-1.0.0.dist-info/RECORD
