Metadata-Version: 2.1
Name: eris
Version: 1.0.0
Summary: Implementation of the Encoding for Robust Immutable Storage (ERIS) encoding
Home-page: https://codeberg.org/eris/python-eris
Author: pukkamustard
Author-email: pukkamustard@posteo.net
Project-URL: Documentation, https://eris.codeberg.page/python-eris/
Project-URL: Bug Tracker, https://codeberg.org/eris/python-eris/issues
Project-URL: Mailing list, https://lists.sr.ht/~pukkamustard/eris
Project-URL: Specification, http://purl.org/eris
Classifier: Programming Language :: Python :: 3
Classifier: License :: OSI Approved :: GNU Affero General Public License v3 or later (AGPLv3+)
Classifier: Operating System :: OS Independent
Classifier: Development Status :: 3 - Alpha
Classifier: Topic :: Communications :: File Sharing
Classifier: Topic :: Internet
Classifier: Topic :: Multimedia
Classifier: Topic :: System :: Archiving
Classifier: Topic :: System :: Archiving :: Mirroring
Requires-Python: >=3.6
License-File: COPYING
Requires-Dist: pycryptodome
Requires-Dist: aiocoap
